tornado_cliff_env/.DS_Store
tornado_cliff_env/__init__.py
tornado_cliff_env/font/Minecraft.ttf
tornado_cliff_env/img/cookie.png
tornado_cliff_env/img/elf_down.png
tornado_cliff_env/img/elf_left.png
tornado_cliff_env/img/elf_right.png
tornado_cliff_env/img/elf_up.png
tornado_cliff_env/img/mountain_bg1.png
tornado_cliff_env/img/mountain_bg2.png
tornado_cliff_env/img/mountain_cliff.png
tornado_cliff_env/img/mountain_near-cliff1.png
tornado_cliff_env/img/mountain_near-cliff2.png
tornado_cliff_env/img/stool.png
tornado_cliff_env/img/tornado.png
tornado_cliff_env/tornadocliffenv.py
tornado_cliff_env/vid/example.gif
tornadocliff_env-0.1.0.dist-info/LICENSE
tornadocliff_env-0.1.0.dist-info/METADATA
tornadocliff_env-0.1.0.dist-info/WHEEL
tornadocliff_env-0.1.0.dist-info/RECORD
