Metadata-Version: 2.1
Name: tornadocliff-env
Version: 0.1.0
Summary: A variation of Gymnasium's CliffWalking enviroment.
Home-page: https://github.com/davera-017/TornadoCliffWalking
License: MIT
Keywords: Reinforcement Learning,RL,CliffWalking,gymnasium,gym
Author: Daniel Ávila Vera
Author-email: davera.017@gmail.com
Requires-Python: >=3.9,<4.0
Classifier: Intended Audience :: Developers
Classifier: Intended Audience :: Education
Classifier: Intended Audience :: Science/Research
Classifier: License :: OSI Approved :: MIT License
Classifier: Operating System :: OS Independent
Classifier: Programming Language :: Python :: 3
Classifier: Programming Language :: Python :: 3.9
Classifier: Programming Language :: Python :: 3.10
Classifier: Programming Language :: Python :: 3.11
Classifier: Programming Language :: Python :: 3 :: Only
Classifier: Topic :: Scientific/Engineering
Classifier: Topic :: Scientific/Engineering :: Artificial Intelligence
Classifier: Topic :: Scientific/Engineering :: Mathematics
Classifier: Topic :: Software Development :: Libraries :: Python Modules
Requires-Dist: gymnasium[toy-text] (==0.28.1)
Requires-Dist: numpy (==1.24.3)
Requires-Dist: pygame (==2.1.3)
Project-URL: Documentation, https://github.com/davera-017/TornadoCliffWalking
Project-URL: Repository, https://github.com/davera-017/TornadoCliffWalking
